unmock/__init__.py
unmock/__version__.py
unmock/core/__init__.py
unmock/core/exceptions.py
unmock/core/http.py
unmock/core/logger.py
unmock/core/logging.yaml
unmock/core/options.py
unmock/core/persistence.py
unmock/core/utils.py
unmock/pytest/__init__.py
unmock/pytest/plugin.py
unmock-0.1.2.dist-info/METADATA
unmock-0.1.2.dist-info/WHEEL
unmock-0.1.2.dist-info/entry_points.txt
unmock-0.1.2.dist-info/top_level.txt
unmock-0.1.2.dist-info/RECORD
