Metadata-Version: 2.1
Name: unmock
Version: 0.1.2
Summary: The Unmock Python clent
Home-page: https://www.unmock.io/
Author: Meeshkan Dev Team
Author-email: dev@meeshkan.com
License: Apache 2.0
Platform: UNKNOWN
Classifier: Development Status :: 3 - Alpha
Classifier: License :: OSI Approved :: MIT License
Classifier: Programming Language :: Python
Classifier: Programming Language :: Python :: 2.7
Classifier: Programming Language :: Python :: 3.4
Classifier: Programming Language :: Python :: 3.5
Classifier: Programming Language :: Python :: 3.6
Classifier: Programming Language :: Python :: 3.7
Classifier: Operating System :: OS Independent
Classifier: Framework :: Pytest
Classifier: Topic :: Software Development :: Testing
Classifier: Topic :: Software Development :: Libraries :: Python Modules
Classifier: Topic :: Software Development :: Testing :: Mocking
Requires-Python: >=2.7.0,!=3.0*,!=3.1*,!=3.2*,!=3.3*
Requires-Dist: requests
Requires-Dist: PyYAML
Requires-Dist: six
Provides-Extra: dev
Requires-Dist: twine ; extra == 'dev'
Requires-Dist: wheel ; extra == 'dev'
Requires-Dist: pytest ; extra == 'dev'
Requires-Dist: coverage ; extra == 'dev'
